fluidly_flask-0.1.3-py3.7-nspkg.pth
fluidly/flask/__init__.py
fluidly/flask/api_exception.py
fluidly/flask/decorators.py
fluidly/flask/exception_handling.py
fluidly/flask/py.typed
fluidly/flask/rest_logger.py
fluidly/flask/utils.py
fluidly/flask/validate_content_type.py
fluidly_flask-0.1.3.dist-info/METADATA
fluidly_flask-0.1.3.dist-info/WHEEL
fluidly_flask-0.1.3.dist-info/namespace_packages.txt
fluidly_flask-0.1.3.dist-info/top_level.txt
fluidly_flask-0.1.3.dist-info/RECORD
