Metadata-Version: 2.1
Name: fluidly-flask
Version: 0.1.3
Summary: Flask helpers.
Home-page: https://github.com/fluidly/python-shared
Author: Fluidly
Author-email: tech@fluidly.com
License: UNKNOWN
Platform: UNKNOWN
Requires-Python: >=3.6.0
Requires-Dist: flask
Requires-Dist: marshmallow
Requires-Dist: uwsgi
Requires-Dist: fluidly-structlog
Requires-Dist: fluidly-auth
